client/__init__.py
client/client.py
client/client/__init__.py
client/client/add_contact.py
client/client/database.py
client/client/del_contact.py
client/client/main_window.py
client/client/main_window_conv.py
client/client/start_dialog.py
client/client/transport.py
client/common/__init__.py
client/common/decos.py
client/common/descriptors.py
client/common/errors.py
client/common/metaclasses.py
client/common/utils.py
client/common/variables.py
client/logs/__init__.py
client/logs/config_client_log.py
client/logs/config_server_log.py
client/unit_tests/__init__.py
client/unit_tests/test_client.py
client/unit_tests/test_server_db.py
client/unit_tests/test_utils.py
PyQt5_python_mess_client-0.1.0.dist-info/METADATA
PyQt5_python_mess_client-0.1.0.dist-info/WHEEL
PyQt5_python_mess_client-0.1.0.dist-info/top_level.txt
PyQt5_python_mess_client-0.1.0.dist-info/RECORD
