Metadata-Version: 2.1
Name: PyQt5-python-mess-client
Version: 0.1.0
Summary: messaging messenger
Author: Alex Devalt
Author-email: alla.mihelson@yandex.ru
Requires-Dist: PyQt5
Requires-Dist: sqlalchemy
Requires-Dist: pycryptodome
Requires-Dist: pycryptodomex
